aiocli/__init__.py
aiocli/commander.py
aiocli/commander_app.py
aiocli/commander_app_wrappers.py
aiocli/helpers.py
aiocli/logger.py
aiocli/py.typed
aiocli/test_utils.py
aiocli-1.12.0.dist-info/licenses/LICENSE
aiocli-1.12.0.dist-info/METADATA
aiocli-1.12.0.dist-info/WHEEL
aiocli-1.12.0.dist-info/top_level.txt
aiocli-1.12.0.dist-info/RECORD
